{"0": "Analysis Editor View", "1": "Frontend Dependencies", "2": "Backend Server & Routing", "3": "Server Cache & Admin Routes", "4": "Content Manager (IndexedDB)", "5": "Backend Package Manifest", "6": "Auth & Upload Middleware", "7": "R2 Storage Client", "8": "Home View & Particle Canvas", "9": "Backend Dependencies", "10": "Frontend API Cache", "11": "Cover Generation Utils", "12": "Project Docs & Rationale", "13": "ESLint Config", "14": "Isolated Iframe Renderer", "15": "JS Config / Path Aliases", "16": "App Bootstrap & Router", "17": "Login Rate Limiter", "18": "Header & Search UI", "19": "Toast Notifications", "20": "Analysis Media Utils", "21": "Analysis Cover Component", "22": "Theme Composable", "23": "Root Dev Scripts", "24": "Cookie Consent", "25": "Contact View", "26": "Vercel Config", "27": "Stateless JWT Auth Flow", "28": "Admin Dashboard", "29": "Admin Login", "30": "Catalog Analysis Card", "31": "Catalog Header", "32": "Vercel Rewrites", "33": "Vite Config", "34": "Cover & Iframe Rationale", "35": "Full-Text Search Fallback", "36": "Cache & Rate-Limit Rationale", "37": "About View", "38": "AdminAnalysisSearch.vue", "39": "AdminLayout.vue", "40": "AnalysisFormFields.vue", "41": "AnalysisMediaModal.vue", "42": "DataTableViewer.vue", "43": "DataVisualizationModal.vue", "44": "LoadComponent.vue", "45": "MeuFooter.vue", "46": "RecentPosts.vue", "47": "ToastContainer.vue", "48": "TopProgressBar.vue", "49": "PostagensDetailView.vue", "50": "Cold start / keep-alive (GET /health)", "51": "CatalogoView.vue", "52": "NotFound.vue", "53": "PesquisaView.vue"}